llm_foundation/__init__.py
llm_foundation/agent_types.py
llm_foundation/basic_structs.py
llm_foundation/extractors.py
llm_foundation/langchain.py
llm_foundation/lm.py
llm_foundation/open_ai.py
llm_foundation/prompts.py
llm_foundation/routing.py
llm_foundation/utils.py
llm_foundation-0.0.28.dist-info/METADATA
llm_foundation-0.0.28.dist-info/WHEEL
llm_foundation-0.0.28.dist-info/licenses/LICENSE
llm_foundation-0.0.28.dist-info/RECORD
